.gitignore
LICENSE
README.md
setup.py
zotero_cli/__init__.py
zotero_cli/backend.py
zotero_cli/cli.py
zotero_cli/common.py
zotero_cli/index.py
zotero_cli.egg-info/PKG-INFO
zotero_cli.egg-info/SOURCES.txt
zotero_cli.egg-info/dependency_links.txt
zotero_cli.egg-info/entry_points.txt
zotero_cli.egg-info/requires.txt
zotero_cli.egg-info/top_level.txt