Metadata-Version: 1.0
Name: zotero-cli
Version: 0.3.0
Summary: Command-line interface for the Zotero API
Home-page: https://github.com/jbaiter/zotero-cli
Author: Johannes Baiter
Author-email: johannes.baiter@gmail.com
License: UNKNOWN
Platform: UNKNOWN
